{"ok":true,"result":[{"update_id":300137958,
"message":{"message_id":2460,"from":{"id":153163864,"first_name":"Andrea"},"chat":{"id":-111667689,"title":"BURB\/cuRE-DESIGN","type":"group"},"date":1464166573,"photo":[{"file_id":"AgADBAADtqgxG1gYIQmruGR0jcsFPvH_QhkABBCSBfNMLm84IF4BAAEC","file_size":1191,"width":90,"height":64},{"file_id":"AgADBAADtqgxG1gYIQmruGR0jcsFPvH_QhkABChoN6fe8GP3IV4BAAEC","file_size":15579,"width":320,"height":226},{"file_id":"AgADBAADtqgxG1gYIQmruGR0jcsFPvH_QhkABCBGTmCcp300Il4BAAEC","file_size":65021,"width":800,"height":565},{"file_id":"AgADBAADtqgxG1gYIQmruGR0jcsFPvH_QhkABNNxK-yJIZm5H14BAAEC","file_size":118735,"width":1280,"height":904}]}},{"update_id":300137959,
"message":{"message_id":2461,"from":{"id":229448758,"first_name":"Jan","last_name":"Weber-Ebnet"},"chat":{"id":-137496804,"title":"BURB\/Young Creating Town","type":"group"},"date":1464166843,"text":"We are at the vaporetto Station \ud83d\ude03"}},{"update_id":300137960,
"message":{"message_id":2462,"from":{"id":153163864,"first_name":"Andrea"},"chat":{"id":-137496804,"title":"BURB\/Young Creating Town","type":"group"},"date":1464166866,"text":"Ok I'm here also"}},{"update_id":300137961,
"message":{"message_id":2463,"from":{"id":153163864,"first_name":"Andrea"},"chat":{"id":-137496804,"title":"BURB\/Young Creating Town","type":"group"},"date":1464169299,"photo":[{"file_id":"AgADBAADt6gxG1gYIQkguheScrG-Pc2WQRkABLMpDVkQXAy8RNgAAgI","file_size":1378,"width":67,"height":90},{"file_id":"AgADBAADt6gxG1gYIQkguheScrG-Pc2WQRkABJJB-rAoMQABhkXYAAIC","file_size":21662,"width":240,"height":320},{"file_id":"AgADBAADt6gxG1gYIQkguheScrG-Pc2WQRkABFW-omRCZ2aYRtgAAgI","file_size":94946,"width":600,"height":800},{"file_id":"AgADBAADt6gxG1gYIQkguheScrG-Pc2WQRkABHjiLne7eKo5Q9gAAgI","file_size":153513,"width":960,"height":1280}]}},{"update_id":300137962,
"message":{"message_id":2464,"from":{"id":153163864,"first_name":"Andrea"},"chat":{"id":-137496804,"title":"BURB\/Young Creating Town","type":"group"},"date":1464170469,"photo":[{"file_id":"AgADBAADuKgxG1gYIQmZMvB4wlCtb6PIYTAABM0HE9FpLN2wdw8CAAEC","file_size":1254,"width":67,"height":90},{"file_id":"AgADBAADuKgxG1gYIQmZMvB4wlCtb6PIYTAABNf4qAJkkU0heA8CAAEC","file_size":25756,"width":240,"height":320},{"file_id":"AgADBAADuKgxG1gYIQmZMvB4wlCtb6PIYTAABB-B_g5sKObkeQ8CAAEC","file_size":149170,"width":600,"height":800},{"file_id":"AgADBAADuKgxG1gYIQmZMvB4wlCtb6PIYTAABIfVomfJBP7Xdg8CAAEC","file_size":282675,"width":960,"height":1280}]}},{"update_id":300137963,
"message":{"message_id":2465,"from":{"id":153163864,"first_name":"Andrea"},"chat":{"id":-137496804,"title":"BURB\/Young Creating Town","type":"group"},"date":1464171088,"photo":[{"file_id":"AgADBAADuagxG1gYIQmFVo5KyJBUdCyaQRkABOZASvaBdCZiMtQAAgI","file_size":1862,"width":67,"height":90},{"file_id":"AgADBAADuagxG1gYIQmFVo5KyJBUdCyaQRkABFQXkNF9j4rAMdQAAgI","file_size":31938,"width":240,"height":320},{"file_id":"AgADBAADuagxG1gYIQmFVo5KyJBUdCyaQRkABM0LzsJLbgJiMNQAAgI","file_size":158431,"width":600,"height":800},{"file_id":"AgADBAADuagxG1gYIQmFVo5KyJBUdCyaQRkABDGR03MkEcGAL9QAAgI","file_size":278957,"width":960,"height":1280}]}},{"update_id":300137964,
"message":{"message_id":2466,"from":{"id":221614416,"first_name":"Miguel","last_name":"Fascioli"},"chat":{"id":-123732933,"title":"BURB\/ArchivioNomadeStalker","type":"group"},"date":1464182390,"text":"Est\u00e1n todos invitados al pabell\u00f3n de Uruguay donde ATI SUFFIX cruza a la biennale urbana con nuestro proyecto REBOOT"}},{"update_id":300137965,
"message":{"message_id":2467,"from":{"id":221614416,"first_name":"Miguel","last_name":"Fascioli"},"chat":{"id":-123732933,"title":"BURB\/ArchivioNomadeStalker","type":"group"},"date":1464182405,"photo":[{"file_id":"AgADAQADq6cxG1CRNQ1ShMUihtmDePPd1i8ABF60pjI-RlwTRGoBAAEC","file_size":725,"width":90,"height":67},{"file_id":"AgADAQADq6cxG1CRNQ1ShMUihtmDePPd1i8ABD7q2qY1Fh08Q2oBAAEC","file_size":6548,"width":320,"height":240},{"file_id":"AgADAQADq6cxG1CRNQ1ShMUihtmDePPd1i8ABC11CK9oDFdMRWoBAAEC","file_size":33238,"width":800,"height":600},{"file_id":"AgADAQADq6cxG1CRNQ1ShMUihtmDePPd1i8ABMGegAeJ0Sa1QmoBAAEC","file_size":66135,"width":1280,"height":960}]}},{"update_id":300137966,
"message":{"message_id":2468,"from":{"id":221614416,"first_name":"Miguel","last_name":"Fascioli"},"chat":{"id":-123732933,"title":"BURB\/ArchivioNomadeStalker","type":"group"},"date":1464182411,"photo":[{"file_id":"AgADAQADrKcxG1CRNQ0WgBM1ZGltnMkC3ikABE5xO_YbqfticHQBAAEC","file_size":1733,"width":90,"height":67},{"file_id":"AgADAQADrKcxG1CRNQ0WgBM1ZGltnMkC3ikABHluCnSv9DlscXQBAAEC","file_size":19707,"width":320,"height":240},{"file_id":"AgADAQADrKcxG1CRNQ0WgBM1ZGltnMkC3ikABGetImxnIQ9rb3QBAAEC","file_size":71920,"width":800,"height":600},{"file_id":"AgADAQADrKcxG1CRNQ0WgBM1ZGltnMkC3ikABDiFjY4KErfobnQBAAEC","file_size":111404,"width":1280,"height":960}]}},{"update_id":300137967,
"message":{"message_id":2469,"from":{"id":153163864,"first_name":"Andrea"},"chat":{"id":-123732933,"title":"BURB\/ArchivioNomadeStalker","type":"group"},"date":1464182575,"text":"#info now at pavilion?","entities":[{"type":"hashtag","offset":0,"length":5}]}},{"update_id":300137968,
"message":{"message_id":2470,"from":{"id":221614416,"first_name":"Miguel","last_name":"Fascioli"},"chat":{"id":-123732933,"title":"BURB\/ArchivioNomadeStalker","type":"group"},"date":1464183402,"photo":[{"file_id":"AgADAQADracxG1CRNQ3AQETZUUCQm57A5y8ABFICBJb01lk6tpsAAgI","file_size":1896,"width":90,"height":67},{"file_id":"AgADAQADracxG1CRNQ3AQETZUUCQm57A5y8ABEc7oYO_ZFLeuJsAAgI","file_size":28778,"width":320,"height":240},{"file_id":"AgADAQADracxG1CRNQ3AQETZUUCQm57A5y8ABEPXYwrSdSaGt5sAAgI","file_size":115909,"width":800,"height":600},{"file_id":"AgADAQADracxG1CRNQ3AQETZUUCQm57A5y8ABPjC4iCF3ZzytZsAAgI","file_size":186848,"width":1280,"height":960}]}},{"update_id":300137969,
"message":{"message_id":2471,"from":{"id":221614416,"first_name":"Miguel","last_name":"Fascioli"},"chat":{"id":-123732933,"title":"BURB\/ArchivioNomadeStalker","type":"group"},"date":1464183406,"photo":[{"file_id":"AgADAQADrqcxG1CRNQ1-1UXP4zPwd_it5y8ABAMD8dFHl5WQm5wAAgI","file_size":1152,"width":90,"height":67},{"file_id":"AgADAQADrqcxG1CRNQ1-1UXP4zPwd_it5y8ABPrFMtkgjGwunJwAAgI","file_size":11161,"width":320,"height":240},{"file_id":"AgADAQADrqcxG1CRNQ1-1UXP4zPwd_it5y8ABDXoOK0SfWnGmpwAAgI","file_size":45094,"width":800,"height":600},{"file_id":"AgADAQADrqcxG1CRNQ1-1UXP4zPwd_it5y8ABNXZOhWQt6UfmZwAAgI","file_size":75992,"width":1280,"height":960}]}},{"update_id":300137970,
"message":{"message_id":2472,"from":{"id":221614416,"first_name":"Miguel","last_name":"Fascioli"},"chat":{"id":-123732933,"title":"BURB\/ArchivioNomadeStalker","type":"group"},"date":1464183411,"photo":[{"file_id":"AgADAQADr6cxG1CRNQ0jkJPk4UW2D9UD3ikABA0o9EIkWwg9mXIBAAEC","file_size":1720,"width":90,"height":67},{"file_id":"AgADAQADr6cxG1CRNQ0jkJPk4UW2D9UD3ikABM9dXWrlb6HnmnIBAAEC","file_size":22777,"width":320,"height":240},{"file_id":"AgADAQADr6cxG1CRNQ0jkJPk4UW2D9UD3ikABMpmK1AP9lJZm3IBAAEC","file_size":91852,"width":800,"height":600},{"file_id":"AgADAQADr6cxG1CRNQ0jkJPk4UW2D9UD3ikABGepHHREY3MkmHIBAAEC","file_size":149308,"width":1280,"height":960}]}},{"update_id":300137971,
"message":{"message_id":2473,"from":{"id":221614416,"first_name":"Miguel","last_name":"Fascioli"},"chat":{"id":-123732933,"title":"BURB\/ArchivioNomadeStalker","type":"group"},"date":1464183416,"photo":[{"file_id":"AgADAQADsKcxG1CRNQ3pWyL77A8UvF2B5y8ABBggeMJVqJxoEZoAAgI","file_size":1488,"width":90,"height":67},{"file_id":"AgADAQADsKcxG1CRNQ3pWyL77A8UvF2B5y8ABEB-WHn2xdNDEpoAAgI","file_size":20610,"width":320,"height":240},{"file_id":"AgADAQADsKcxG1CRNQ3pWyL77A8UvF2B5y8ABH6oLBA_2neaE5oAAgI","file_size":88232,"width":800,"height":600},{"file_id":"AgADAQADsKcxG1CRNQ3pWyL77A8UvF2B5y8ABKTdfg0hCuJOEJoAAgI","file_size":146565,"width":1280,"height":960}]}},{"update_id":300137972,
"message":{"message_id":2474,"from":{"id":180170485,"first_name":"Lorenzo"},"chat":{"id":-123732933,"title":"BURB\/ArchivioNomadeStalker","type":"group"},"date":1464183477,"text":"I can be there in one hour,  I need help to transpass the border...  How many passages you can menage?"}},{"update_id":300137973,
"message":{"message_id":2475,"from":{"id":192911864,"first_name":"Beatrice","last_name":"Pellos"},"chat":{"id":-123732933,"title":"BURB\/ArchivioNomadeStalker","type":"group"},"date":1464185235,"text":"#info how can we enter","entities":[{"type":"hashtag","offset":0,"length":5}]}},{"update_id":300137974,
"message":{"message_id":2476,"from":{"id":180170485,"first_name":"Lorenzo"},"chat":{"id":-123732933,"title":"BURB\/ArchivioNomadeStalker","type":"group"},"date":1464185491,"text":"I can hide in a coffe beans sack\n.."}},{"update_id":300137975,
"message":{"message_id":2477,"from":{"id":231246063,"first_name":"Felicia"},"chat":{"id":-137496804,"title":"BURB\/Young Creating Town","type":"group"},"date":1464188037,"new_chat_participant":{"id":171153102,"first_name":"Sophie","last_name":"\u0950"},"new_chat_member":{"id":171153102,"first_name":"Sophie","last_name":"\u0950"}}},{"update_id":300137976,
"message":{"message_id":2478,"from":{"id":229448758,"first_name":"Jan","last_name":"Weber-Ebnet"},"chat":{"id":-137496804,"title":"BURB\/Young Creating Town","type":"group"},"date":1464188067,"photo":[{"file_id":"AgADAgADzqcxGzYcrQ1LOieSvvbIp8z5hSoABM9A-UfjNl9WHCcCAAEC","file_size":1911,"width":67,"height":90},{"file_id":"AgADAgADzqcxGzYcrQ1LOieSvvbIp8z5hSoABBjt16uF1EMnHScCAAEC","file_size":31229,"width":240,"height":320},{"file_id":"AgADAgADzqcxGzYcrQ1LOieSvvbIp8z5hSoABFBC1E6WQpwsHicCAAEC","file_size":145849,"width":600,"height":800},{"file_id":"AgADAgADzqcxGzYcrQ1LOieSvvbIp8z5hSoABB3O2uDUSP2nGycCAAEC","file_size":252931,"width":960,"height":1280}]}},{"update_id":300137977,
"message":{"message_id":2479,"from":{"id":229448758,"first_name":"Jan","last_name":"Weber-Ebnet"},"chat":{"id":-137496804,"title":"BURB\/Young Creating Town","type":"group"},"date":1464188077,"photo":[{"file_id":"AgADAgADz6cxGzYcrQ1_10oURwfMYZnORw0ABL4fYmnzAc1JgqwAAgI","file_size":1502,"width":90,"height":67},{"file_id":"AgADAgADz6cxGzYcrQ1_10oURwfMYZnORw0ABHC30VporHCUg6wAAgI","file_size":27999,"width":320,"height":240},{"file_id":"AgADAgADz6cxGzYcrQ1_10oURwfMYZnORw0ABLDH1Pob_wKNhawAAgI","file_size":125283,"width":800,"height":600},{"file_id":"AgADAgADz6cxGzYcrQ1_10oURwfMYZnORw0ABP8P9kXOGZmEhKwAAgI","file_size":208419,"width":1280,"height":960}]}},{"update_id":300137978,
"message":{"message_id":2480,"from":{"id":229448758,"first_name":"Jan","last_name":"Weber-Ebnet"},"chat":{"id":-137496804,"title":"BURB\/Young Creating Town","type":"group"},"date":1464188135,"photo":[{"file_id":"AgADAgAD0KcxGzYcrQ0vHov0vI0sPc4QSA0ABI7Nz71E6PHEbqwAAgI","file_size":2073,"width":67,"height":90},{"file_id":"AgADAgAD0KcxGzYcrQ0vHov0vI0sPc4QSA0ABMh9_qgJfkCIb6wAAgI","file_size":34349,"width":240,"height":320},{"file_id":"AgADAgAD0KcxGzYcrQ0vHov0vI0sPc4QSA0ABDNROHi1sdPlcKwAAgI","file_size":153513,"width":600,"height":800},{"file_id":"AgADAgAD0KcxGzYcrQ0vHov0vI0sPc4QSA0ABLYigCw2pd0obawAAgI","file_size":262338,"width":960,"height":1280}]}},{"update_id":300137979,
"message":{"message_id":2481,"from":{"id":192911864,"first_name":"Beatrice","last_name":"Pellos"},"chat":{"id":-123732933,"title":"BURB\/ArchivioNomadeStalker","type":"group"},"date":1464188346,"text":"#info me and Camilla we are outside can you come to pickup us?","entities":[{"type":"hashtag","offset":0,"length":5}]}},{"update_id":300137980,
"message":{"message_id":2482,"from":{"id":180170485,"first_name":"Lorenzo"},"chat":{"id":-123732933,"title":"BURB\/ArchivioNomadeStalker","type":"group"},"date":1464189468,"new_chat_participant":{"id":189458894,"first_name":"Matthew","last_name":"Ashton"},"new_chat_member":{"id":189458894,"first_name":"Matthew","last_name":"Ashton"}}},{"update_id":300137981,
"message":{"message_id":2483,"from":{"id":187366683,"first_name":"Carla","last_name":"Nanni"},"chat":{"id":-137496804,"title":"BURB\/Young Creating Town","type":"group"},"date":1464189688,"text":"Bravissimi!! Very good!"}},{"update_id":300137982,
"message":{"message_id":2484,"from":{"id":229448758,"first_name":"Jan","last_name":"Weber-Ebnet"},"chat":{"id":-137496804,"title":"BURB\/Young Creating Town","type":"group"},"date":1464190193,"photo":[{"file_id":"AgADAgAD0acxGzYcrQ2jW0o2erkFTG3IRw0ABLObI6Ws47TTA64AAgI","file_size":1527,"width":67,"height":90},{"file_id":"AgADAgAD0acxGzYcrQ2jW0o2erkFTG3IRw0ABBDH1sW_OvNwBK4AAgI","file_size":19828,"width":240,"height":320},{"file_id":"AgADAgAD0acxGzYcrQ2jW0o2erkFTG3IRw0ABL5Y9atVGidxBa4AAgI","file_size":85639,"width":600,"height":800},{"file_id":"AgADAgAD0acxGzYcrQ2jW0o2erkFTG3IRw0ABA6eR2Z_FXbYAq4AAgI","file_size":143366,"width":960,"height":1280}]}},{"update_id":300137983,
"message":{"message_id":2485,"from":{"id":204441421,"first_name":"Lorenzo","last_name":"Bottiglieri"},"chat":{"id":-123732933,"title":"BURB\/ArchivioNomadeStalker","type":"group"},"date":1464192151,"photo":[{"file_id":"AgADBAADuKcxG02HLwyaP0gdjK5fYQm5WDAABO1pXlvhU2gIrl0AAgI","file_size":860,"width":90,"height":67},{"file_id":"AgADBAADuKcxG02HLwyaP0gdjK5fYQm5WDAABIpfkMJW5merr10AAgI","file_size":11371,"width":320,"height":240},{"file_id":"AgADBAADuKcxG02HLwyaP0gdjK5fYQm5WDAABCS-6yB8ew7qsF0AAgI","file_size":48878,"width":800,"height":600},{"file_id":"AgADBAADuKcxG02HLwyaP0gdjK5fYQm5WDAABI6r2e92fhWIrV0AAgI","file_size":81083,"width":1280,"height":960}]}},{"update_id":300137984,
"message":{"message_id":2486,"from":{"id":204441421,"first_name":"Lorenzo","last_name":"Bottiglieri"},"chat":{"id":-123732933,"title":"BURB\/ArchivioNomadeStalker","type":"group"},"date":1464194602,"photo":[{"file_id":"AgADBAADuacxG02HLwz4sz3fLPrWAiorQxkABAOc28fWSOBfF2EBAAEC","file_size":1867,"width":67,"height":90},{"file_id":"AgADBAADuacxG02HLwz4sz3fLPrWAiorQxkABG7lmwrqPdkZFmEBAAEC","file_size":27417,"width":240,"height":320},{"file_id":"AgADBAADuacxG02HLwz4sz3fLPrWAiorQxkABI0bu9j3m7cbGGEBAAEC","file_size":132239,"width":600,"height":800},{"file_id":"AgADBAADuacxG02HLwz4sz3fLPrWAiorQxkABKFY7wMoLHg3GWEBAAEC","file_size":272621,"width":960,"height":1280}]}},{"update_id":300137985,
"message":{"message_id":2487,"from":{"id":204441421,"first_name":"Lorenzo","last_name":"Bottiglieri"},"chat":{"id":-123732933,"title":"BURB\/ArchivioNomadeStalker","type":"group"},"date":1464194610,"text":"Another guest.."}},{"update_id":300137986,
"message":{"message_id":2488,"from":{"id":187616059,"first_name":"Giulia","last_name":"Mazzorin"},"chat":{"id":-137496804,"title":"BURB\/Young Creating Town","type":"group"},"date":1464199701,"photo":[{"file_id":"AgADBAADS6gxGzvLLgu4_BwTvz2hmNDjijAABJfDCKQzb9-U_FoAAgI","file_size":1721,"width":90,"height":90},{"file_id":"AgADBAADS6gxGzvLLgu4_BwTvz2hmNDjijAABJPCjX2d9bP1-1oAAgI","file_size":29775,"width":320,"height":320},{"file_id":"AgADBAADS6gxGzvLLgu4_BwTvz2hmNDjijAABHEidV_yYwpX_VoAAgI","file_size":156350,"width":800,"height":800},{"file_id":"AgADBAADS6gxGzvLLgu4_BwTvz2hmNDjijAABGpdJFB3mNv6-loAAgI","file_size":320105,"width":1280,"height":1280}]}},{"update_id":300137987,
"message":{"message_id":2489,"from":{"id":187616059,"first_name":"Giulia","last_name":"Mazzorin"},"chat":{"id":-137496804,"title":"BURB\/Young Creating Town","type":"group"},"date":1464199794,"photo":[{"file_id":"AgADBAADTKgxGzvLLgtRZ0WlKZscZ5gYizAABOJgTTDrk1ymQQUCAAEC","file_size":1978,"width":90,"height":90},{"file_id":"AgADBAADTKgxGzvLLgtRZ0WlKZscZ5gYizAABAKbn2pYKFu4QgUCAAEC","file_size":33544,"width":320,"height":320},{"file_id":"AgADBAADTKgxGzvLLgtRZ0WlKZscZ5gYizAABIAsU6zeDiuSQAUCAAEC","file_size":153434,"width":800,"height":800},{"file_id":"AgADBAADTKgxGzvLLgtRZ0WlKZscZ5gYizAABOf04tTwQWZrPwUCAAEC","file_size":291482,"width":1280,"height":1280}]}},{"update_id":300137988,
"message":{"message_id":2490,"from":{"id":221614416,"first_name":"Miguel","last_name":"Fascioli"},"chat":{"id":-123732933,"title":"BURB\/ArchivioNomadeStalker","type":"group"},"date":1464217834,"text":"I gave Lorenzo some invitations for the opening tomorrow at 16:45. Sorry but we are not connected all the time. Hope we see each other at giardini then. Buonna notte ;)"}},{"update_id":300137989,
"message":{"message_id":2491,"from":{"id":114880316,"first_name":"Francesco","last_name":"Careri","username":"PICCIO17"},"chat":{"id":-137496804,"title":"BURB\/Young Creating Town","type":"group"},"date":1464247277,"text":"Incredibile!! \ud83d\ude18\ud83d\ude18\ud83d\ude18"}},{"update_id":300137990,
"message":{"message_id":2492,"from":{"id":180170485,"first_name":"Lorenzo"},"chat":{"id":-123732933,"title":"BURB\/ArchivioNomadeStalker","type":"group"},"date":1464247689,"new_chat_participant":{"id":218945727,"first_name":"Enri","username":"ilveropera"},"new_chat_member":{"id":218945727,"first_name":"Enri","username":"ilveropera"}}}]}